curl_fetch2py/__init__.py
curl_fetch2py/api.py
curl_fetch2py-0.1.dist-info/METADATA
curl_fetch2py-0.1.dist-info/WHEEL
curl_fetch2py-0.1.dist-info/top_level.txt
curl_fetch2py-0.1.dist-info/RECORD
