Metadata-Version: 2.1
Name: curl_fetch2py
Version: 0.1
Summary: CurlFetch2Py - это библиотека на Python, предназначенная для парсинга команд curl и fetch, преобразуя их в структурированные объекты Python
Home-page: https://github.com/Yakvenalex/curl_fetch2py
Author: Alexey Yakovenko
Author-email: mr.mnogo@gmail.com
Classifier: Programming Language :: Python :: 3
Classifier: License :: OSI Approved :: MIT License
Classifier: Operating System :: OS Independent
Requires-Python: >=3.6
